[
  {
    "Id": 111,
    "Name": "Laptops",
    "FatherCategoryId": 103,
    "Title": "Laptops",
    "Description": "This is a generic description of a Category.",
    "Keywords": "Laptops",
    "IsActive": false,
    "LomadeeCampaignCode": "",
    "AdWordsRemarketingCode": "",
    "ShowInStoreFront": true,
    "ShowBrandFilter": true,
    "ActiveStoreFrontLink": true,
    "GlobalCategoryId": 0,
    "StockKeepingUnitSelectionMode": "SPECIFICATION",
    "Score": 3,
    "LinkId": "Laptops",
    "HasChildren": false
  },
  {
    "Id": 107,
    "Name": "Mixers & Blenders",
    "FatherCategoryId": 102,
    "Title": "Mixers & Blender",
    "Description": "This is a generic description of a Category.",
    "Keywords": "Mixers & Blender",
    "IsActive": false,
    "LomadeeCampaignCode": "",
    "AdWordsRemarketingCode": "",
    "ShowInStoreFront": true,
    "ShowBrandFilter": true,
    "ActiveStoreFrontLink": true,
    "GlobalCategoryId": 0,
    "StockKeepingUnitSelectionMode": "SPECIFICATION",
    "Score": 3,
    "LinkId": "Mixers---Blenders",
    "HasChildren": false
  },
  {
    "Id": 110,
    "Name": "TVs",
    "FatherCategoryId": 103,
    "Title": "TVs",
    "Description": "This is a generic description of a Category.",
    "Keywords": "TVs",
    "IsActive": false,
    "LomadeeCampaignCode": "",
    "AdWordsRemarketingCode": "",
    "ShowInStoreFront": true,
    "ShowBrandFilter": true,
    "ActiveStoreFrontLink": true,
    "GlobalCategoryId": 0,
    "StockKeepingUnitSelectionMode": "SPECIFICATION",
    "Score": 3,
    "LinkId": "TVs",
    "HasChildren": false
  },
  {
    "Id": 114,
    "Name": "Main Category",
    "FatherCategoryId": null,
    "Title": "My Main Category",
    "Description": "",
    "Keywords": "main, parent",
    "IsActive": true,
    "LomadeeCampaignCode": "",
    "AdWordsRemarketingCode": "",
    "ShowInStoreFront": false,
    "ShowBrandFilter": false,
    "ActiveStoreFrontLink": false,
    "GlobalCategoryId": 2092,
    "StockKeepingUnitSelectionMode": "SPECIFICATION",
    "Score": null,
    "LinkId": "Main-Category",
    "HasChildren": false
  },
  {
    "Id": 109,
    "Name": "Coffee Makers",
    "FatherCategoryId": 102,
    "Title": "Coffee Makers",
    "Description": "This is a generic description of a Category.",
    "Keywords": "Coffee Makers",
    "IsActive": false,
    "LomadeeCampaignCode": "",
    "AdWordsRemarketingCode": "",
    "ShowInStoreFront": true,
    "ShowBrandFilter": true,
    "ActiveStoreFrontLink": true,
    "GlobalCategoryId": 0,
    "StockKeepingUnitSelectionMode": "SPECIFICATION",
    "Score": 3,
    "LinkId": "Coffee-Makers",
    "HasChildren": false
  },
  {
    "Id": 103,
    "Name": "Electronics",
    "FatherCategoryId": null,
    "Title": "Electronics",
    "Description": "This is a generic description of a Department.",
    "Keywords": "Electronics",
    "IsActive": true,
    "LomadeeCampaignCode": "",
    "AdWordsRemarketingCode": "",
    "ShowInStoreFront": false,
    "ShowBrandFilter": false,
    "ActiveStoreFrontLink": false,
    "GlobalCategoryId": 222,
    "StockKeepingUnitSelectionMode": "SPECIFICATION",
    "Score": 0,
    "LinkId": "Electronics",
    "HasChildren": true
  },
  {
    "Id": 101,
    "Name": "Major Appliances",
    "FatherCategoryId": null,
    "Title": "Home Appliances",
    "Description": "This is a generic description of a Department.",
    "Keywords": "Major Appliances",
    "IsActive": false,
    "LomadeeCampaignCode": "",
    "AdWordsRemarketingCode": "",
    "ShowInStoreFront": false,
    "ShowBrandFilter": false,
    "ActiveStoreFrontLink": false,
    "GlobalCategoryId": 604,
    "StockKeepingUnitSelectionMode": "SPECIFICATION",
    "Score": 0,
    "LinkId": "Major-Appliances",
    "HasChildren": true
  },
  {
    "Id": 1,
    "Name": "Test Category - updated",
    "FatherCategoryId": null,
    "Title": "Category_Page_Title",
    "Description": "Brief description of the category. It is advisable not to exceed 150 characters so that the search engines can show it correctly in the search results;",
    "Keywords": "",
    "IsActive": false,
    "LomadeeCampaignCode": "",
    "AdWordsRemarketingCode": "",
    "ShowInStoreFront": false,
    "ShowBrandFilter": false,
    "ActiveStoreFrontLink": false,
    "GlobalCategoryId": 783,
    "StockKeepingUnitSelectionMode": "LIST",
    "Score": null,
    "LinkId": "Test-Category---updated",
    "HasChildren": false
  },
  {
    "Id": 102,
    "Name": "Small Appliances",
    "FatherCategoryId": 180,
    "Title": "Small Appliances",
    "Description": null,
    "Keywords": null,
    "IsActive": false,
    "LomadeeCampaignCode": null,
    "AdWordsRemarketingCode": null,
    "ShowInStoreFront": false,
    "ShowBrandFilter": false,
    "ActiveStoreFrontLink": false,
    "GlobalCategoryId": 0,
    "StockKeepingUnitSelectionMode": "SPECIFICATION",
    "Score": null,
    "LinkId": "Small-Appliances",
    "HasChildren": true
  },
  {
    "Id": 112,
    "Name": "Cameras",
    "FatherCategoryId": 103,
    "Title": "Cameras",
    "Description": "This is a generic description of a Category.",
    "Keywords": "Camers",
    "IsActive": true,
    "LomadeeCampaignCode": "",
    "AdWordsRemarketingCode": "",
    "ShowInStoreFront": true,
    "ShowBrandFilter": true,
    "ActiveStoreFrontLink": true,
    "GlobalCategoryId": 2096,
    "StockKeepingUnitSelectionMode": "SPECIFICATION",
    "Score": 3,
    "LinkId": "Cameras",
    "HasChildren": false
  },
  {
    "Id": 105,
    "Name": "Ranges & Ovens",
    "FatherCategoryId": 101,
    "Title": "Ranges & Ovens",
    "Description": "This is a generic description of a Department.",
    "Keywords": "Ranges & Ovens",
    "IsActive": true,
    "LomadeeCampaignCode": "",
    "AdWordsRemarketingCode": "",
    "ShowInStoreFront": true,
    "ShowBrandFilter": true,
    "ActiveStoreFrontLink": true,
    "GlobalCategoryId": 5181,
    "StockKeepingUnitSelectionMode": "SPECIFICATION",
    "Score": 3,
    "LinkId": "Ranges---Ovens",
    "HasChildren": false
  },
  {
    "Id": 172,
    "Name": "Soaps",
    "FatherCategoryId": 171,
    "Title": "Soaps",
    "Description": "Soaps",
    "Keywords": "Soaps",
    "IsActive": false,
    "LomadeeCampaignCode": "",
    "AdWordsRemarketingCode": "",
    "ShowInStoreFront": true,
    "ShowBrandFilter": true,
    "ActiveStoreFrontLink": true,
    "GlobalCategoryId": 491,
    "StockKeepingUnitSelectionMode": "LIST",
    "Score": null,
    "LinkId": "Soaps",
    "HasChildren": false
  },
  {
    "Id": 189,
    "Name": "category2",
    "FatherCategoryId": null,
    "Title": "Shop",
    "Description": "Shop wallpapers & Murals",
    "Keywords": "Shop",
    "IsActive": true,
    "LomadeeCampaignCode": "",
    "AdWordsRemarketingCode": "",
    "ShowInStoreFront": false,
    "ShowBrandFilter": false,
    "ActiveStoreFrontLink": false,
    "GlobalCategoryId": 1,
    "StockKeepingUnitSelectionMode": "SPECIFICATION",
    "Score": null,
    "LinkId": "category2",
    "HasChildren": false
  },
  {
    "Id": 178,
    "Name": "Boots",
    "FatherCategoryId": 177,
    "Title": "Boots",
    "Description": "Boots for kids",
    "Keywords": "Wellington,gumboot,knee boot,thigh boot,half-boot",
    "IsActive": false,
    "LomadeeCampaignCode": "",
    "AdWordsRemarketingCode": "",
    "ShowInStoreFront": true,
    "ShowBrandFilter": true,
    "ActiveStoreFrontLink": true,
    "GlobalCategoryId": 166,
    "StockKeepingUnitSelectionMode": "COMBO",
    "Score": null,
    "LinkId": "Boots",
    "HasChildren": false
  },
  {
    "Id": 186,
    "Name": "c",
    "FatherCategoryId": null,
    "Title": "Shop",
    "Description": "Shop wallpapers & Murals",
    "Keywords": "Shop",
    "IsActive": false,
    "LomadeeCampaignCode": null,
    "AdWordsRemarketingCode": null,
    "ShowInStoreFront": false,
    "ShowBrandFilter": false,
    "ActiveStoreFrontLink": false,
    "GlobalCategoryId": 1,
    "StockKeepingUnitSelectionMode": "SPECIFICATION",
    "Score": null,
    "LinkId": "c",
    "HasChildren": false
  },
  {
    "Id": 188,
    "Name": "category3",
    "FatherCategoryId": null,
    "Title": "Shop",
    "Description": "Shop wallpapers & Murals",
    "Keywords": "Shop",
    "IsActive": true,
    "LomadeeCampaignCode": "",
    "AdWordsRemarketingCode": "",
    "ShowInStoreFront": false,
    "ShowBrandFilter": false,
    "ActiveStoreFrontLink": false,
    "GlobalCategoryId": 1,
    "StockKeepingUnitSelectionMode": "SPECIFICATION",
    "Score": null,
    "LinkId": "category3",
    "HasChildren": false
  },
  {
    "Id": 151,
    "Name": "Bird Statues",
    "FatherCategoryId": 126,
    "Title": "",
    "Description": "",
    "Keywords": "",
    "IsActive": false,
    "LomadeeCampaignCode": "",
    "AdWordsRemarketingCode": "",
    "ShowInStoreFront": false,
    "ShowBrandFilter": false,
    "ActiveStoreFrontLink": true,
    "GlobalCategoryId": 536,
    "StockKeepingUnitSelectionMode": "LIST",
    "Score": null,
    "LinkId": "Bird-Statues",
    "HasChildren": false
  },
  {
    "Id": 174,
    "Name": "Shoes",
    "FatherCategoryId": 173,
    "Title": "Shoes",
    "Description": "Shoes",
    "Keywords": "Shoe,Sneakers, boot, loafer, flip-flops, basketball shoe, slipper",
    "IsActive": false,
    "LomadeeCampaignCode": "",
    "AdWordsRemarketingCode": "",
    "ShowInStoreFront": true,
    "ShowBrandFilter": true,
    "ActiveStoreFrontLink": true,
    "GlobalCategoryId": 166,
    "StockKeepingUnitSelectionMode": "LIST",
    "Score": null,
    "LinkId": "Shoes",
    "HasChildren": true
  },
  {
    "Id": 162,
    "Name": "Gothic & Medieval",
    "FatherCategoryId": 115,
    "Title": "",
    "Description": "",
    "Keywords": "",
    "IsActive": false,
    "LomadeeCampaignCode": "",
    "AdWordsRemarketingCode": "",
    "ShowInStoreFront": false,
    "ShowBrandFilter": false,
    "ActiveStoreFrontLink": true,
    "GlobalCategoryId": 536,
    "StockKeepingUnitSelectionMode": "LIST",
    "Score": null,
    "LinkId": "Gothic---Medieval",
    "HasChildren": false
  },
  {
    "Id": 157,
    "Name": "BIGFOOT AND YETIS",
    "FatherCategoryId": 130,
    "Title": "",
    "Description": "",
    "Keywords": "",
    "IsActive": false,
    "LomadeeCampaignCode": "",
    "AdWordsRemarketingCode": "",
    "ShowInStoreFront": false,
    "ShowBrandFilter": false,
    "ActiveStoreFrontLink": true,
    "GlobalCategoryId": 536,
    "StockKeepingUnitSelectionMode": "LIST",
    "Score": null,
    "LinkId": "BIGFOOT-AND-YETIS",
    "HasChildren": false
  },
  {
    "Id": 184,
    "Name": "c",
    "FatherCategoryId": null,
    "Title": "Shop",
    "Description": "Shop wallpapers & Murals",
    "Keywords": "Shop",
    "IsActive": false,
    "LomadeeCampaignCode": null,
    "AdWordsRemarketingCode": null,
    "ShowInStoreFront": false,
    "ShowBrandFilter": false,
    "ActiveStoreFrontLink": false,
    "GlobalCategoryId": 1,
    "StockKeepingUnitSelectionMode": "SPECIFICATION",
    "Score": null,
    "LinkId": "c",
    "HasChildren": false
  },
  {
    "Id": 164,
    "Name": "Religious Statues",
    "FatherCategoryId": 115,
    "Title": "",
    "Description": "",
    "Keywords": "",
    "IsActive": false,
    "LomadeeCampaignCode": "",
    "AdWordsRemarketingCode": "",
    "ShowInStoreFront": false,
    "ShowBrandFilter": false,
    "ActiveStoreFrontLink": true,
    "GlobalCategoryId": 536,
    "StockKeepingUnitSelectionMode": "LIST",
    "Score": null,
    "LinkId": "Religious-Statues",
    "HasChildren": false
  },
  {
    "Id": 152,
    "Name": "CHILDREN",
    "FatherCategoryId": 127,
    "Title": "",
    "Description": "",
    "Keywords": "",
    "IsActive": false,
    "LomadeeCampaignCode": "",
    "AdWordsRemarketingCode": "",
    "ShowInStoreFront": false,
    "ShowBrandFilter": false,
    "ActiveStoreFrontLink": true,
    "GlobalCategoryId": 536,
    "StockKeepingUnitSelectionMode": "LIST",
    "Score": null,
    "LinkId": "CHILDREN",
    "HasChildren": false
  },
  {
    "Id": 140,
    "Name": "Egyptian Home Accents",
    "FatherCategoryId": 122,
    "Title": "",
    "Description": "",
    "Keywords": "",
    "IsActive": false,
    "LomadeeCampaignCode": "",
    "AdWordsRemarketingCode": "",
    "ShowInStoreFront": false,
    "ShowBrandFilter": false,
    "ActiveStoreFrontLink": true,
    "GlobalCategoryId": 8,
    "StockKeepingUnitSelectionMode": "LIST",
    "Score": null,
    "LinkId": "Egyptian-Home-Accents",
    "HasChildren": false
  },
  {
    "Id": 139,
    "Name": "Egyptian Statues",
    "FatherCategoryId": 122,
    "Title": "",
    "Description": "",
    "Keywords": "",
    "IsActive": false,
    "LomadeeCampaignCode": "",
    "AdWordsRemarketingCode": "",
    "ShowInStoreFront": false,
    "ShowBrandFilter": false,
    "ActiveStoreFrontLink": true,
    "GlobalCategoryId": 8,
    "StockKeepingUnitSelectionMode": "LIST",
    "Score": null,
    "LinkId": "Egyptian-Statues",
    "HasChildren": false
  },
  {
    "Id": 163,
    "Name": "Gutter Downspout Statues",
    "FatherCategoryId": 115,
    "Title": "",
    "Description": "",
    "Keywords": "",
    "IsActive": false,
    "LomadeeCampaignCode": "",
    "AdWordsRemarketingCode": "",
    "ShowInStoreFront": false,
    "ShowBrandFilter": false,
    "ActiveStoreFrontLink": true,
    "GlobalCategoryId": 536,
    "StockKeepingUnitSelectionMode": "LIST",
    "Score": null,
    "LinkId": "Gutter-Downspout-Statues",
    "HasChildren": false
  },
  {
    "Id": 142,
    "Name": "Egyptian Furniture",
    "FatherCategoryId": 122,
    "Title": "",
    "Description": "",
    "Keywords": "",
    "IsActive": false,
    "LomadeeCampaignCode": "",
    "AdWordsRemarketingCode": "",
    "ShowInStoreFront": false,
    "ShowBrandFilter": false,
    "ActiveStoreFrontLink": true,
    "GlobalCategoryId": 8,
    "StockKeepingUnitSelectionMode": "LIST",
    "Score": null,
    "LinkId": "Egyptian-Furniture",
    "HasChildren": false
  },
  {
    "Id": 104,
    "Name": "Refrigerators",
    "FatherCategoryId": 101,
    "Title": "Refrigerators",
    "Description": "This is a generic description of a Department.",
    "Keywords": "Refrigerators",
    "IsActive": true,
    "LomadeeCampaignCode": "",
    "AdWordsRemarketingCode": "",
    "ShowInStoreFront": true,
    "ShowBrandFilter": true,
    "ActiveStoreFrontLink": true,
    "GlobalCategoryId": 730,
    "StockKeepingUnitSelectionMode": "SPECIFICATION",
    "Score": 3,
    "LinkId": "Refrigerators",
    "HasChildren": false
  },
  {
    "Id": 115,
    "Name": "GARDEN",
    "FatherCategoryId": 180,
    "Title": "GARDEN",
    "Description": null,
    "Keywords": null,
    "IsActive": false,
    "LomadeeCampaignCode": null,
    "AdWordsRemarketingCode": null,
    "ShowInStoreFront": false,
    "ShowBrandFilter": false,
    "ActiveStoreFrontLink": false,
    "GlobalCategoryId": 0,
    "StockKeepingUnitSelectionMode": "LIST",
    "Score": null,
    "LinkId": "GARDEN",
    "HasChildren": true
  },
  {
    "Id": 117,
    "Name": "FURNITURE",
    "FatherCategoryId": 180,
    "Title": "",
    "Description": null,
    "Keywords": null,
    "IsActive": false,
    "LomadeeCampaignCode": null,
    "AdWordsRemarketingCode": null,
    "ShowInStoreFront": false,
    "ShowBrandFilter": false,
    "ActiveStoreFrontLink": false,
    "GlobalCategoryId": 0,
    "StockKeepingUnitSelectionMode": "LIST",
    "Score": null,
    "LinkId": "FURNITURE",
    "HasChildren": false
  },
  {
    "Id": 129,
    "Name": "Angel & Cherub Statues",
    "FatherCategoryId": 115,
    "Title": "",
    "Description": "",
    "Keywords": "",
    "IsActive": false,
    "LomadeeCampaignCode": "",
    "AdWordsRemarketingCode": "",
    "ShowInStoreFront": false,
    "ShowBrandFilter": false,
    "ActiveStoreFrontLink": true,
    "GlobalCategoryId": 536,
    "StockKeepingUnitSelectionMode": "LIST",
    "Score": null,
    "LinkId": "Angel---Cherub-Statues",
    "HasChildren": false
  },
  {
    "Id": 128,
    "Name": "Memorial Statues",
    "FatherCategoryId": 115,
    "Title": "",
    "Description": "",
    "Keywords": "",
    "IsActive": false,
    "LomadeeCampaignCode": "",
    "AdWordsRemarketingCode": "",
    "ShowInStoreFront": false,
    "ShowBrandFilter": false,
    "ActiveStoreFrontLink": true,
    "GlobalCategoryId": 536,
    "StockKeepingUnitSelectionMode": "LIST",
    "Score": null,
    "LinkId": "Memorial-Statues",
    "HasChildren": false
  },
  {
    "Id": 158,
    "Name": "GNOMES",
    "FatherCategoryId": 130,
    "Title": "",
    "Description": "",
    "Keywords": "",
    "IsActive": false,
    "LomadeeCampaignCode": "",
    "AdWordsRemarketingCode": "",
    "ShowInStoreFront": false,
    "ShowBrandFilter": false,
    "ActiveStoreFrontLink": true,
    "GlobalCategoryId": 536,
    "StockKeepingUnitSelectionMode": "LIST",
    "Score": null,
    "LinkId": "GNOMES",
    "HasChildren": false
  },
  {
    "Id": 127,
    "Name": "Bronze Statuary",
    "FatherCategoryId": 115,
    "Title": "",
    "Description": "",
    "Keywords": "",
    "IsActive": false,
    "LomadeeCampaignCode": "",
    "AdWordsRemarketingCode": "",
    "ShowInStoreFront": false,
    "ShowBrandFilter": false,
    "ActiveStoreFrontLink": true,
    "GlobalCategoryId": 536,
    "StockKeepingUnitSelectionMode": "LIST",
    "Score": null,
    "LinkId": "Bronze-Statuary",
    "HasChildren": true
  },
  {
    "Id": 141,
    "Name": "Egyptian Wall Decor",
    "FatherCategoryId": 122,
    "Title": "",
    "Description": "",
    "Keywords": "",
    "IsActive": false,
    "LomadeeCampaignCode": "",
    "AdWordsRemarketingCode": "",
    "ShowInStoreFront": false,
    "ShowBrandFilter": false,
    "ActiveStoreFrontLink": true,
    "GlobalCategoryId": 8,
    "StockKeepingUnitSelectionMode": "LIST",
    "Score": null,
    "LinkId": "Egyptian-Wall-Decor",
    "HasChildren": false
  },
  {
    "Id": 147,
    "Name": "Woodland Animals",
    "FatherCategoryId": 126,
    "Title": "",
    "Description": "",
    "Keywords": "",
    "IsActive": false,
    "LomadeeCampaignCode": "",
    "AdWordsRemarketingCode": "",
    "ShowInStoreFront": false,
    "ShowBrandFilter": false,
    "ActiveStoreFrontLink": true,
    "GlobalCategoryId": 536,
    "StockKeepingUnitSelectionMode": "LIST",
    "Score": null,
    "LinkId": "Woodland-Animals",
    "HasChildren": false
  },
  {
    "Id": 123,
    "Name": "BASIL STREET",
    "FatherCategoryId": 180,
    "Title": "",
    "Description": null,
    "Keywords": null,
    "IsActive": false,
    "LomadeeCampaignCode": null,
    "AdWordsRemarketingCode": null,
    "ShowInStoreFront": false,
    "ShowBrandFilter": false,
    "ActiveStoreFrontLink": false,
    "GlobalCategoryId": 0,
    "StockKeepingUnitSelectionMode": "LIST",
    "Score": null,
    "LinkId": "BASIL-STREET",
    "HasChildren": true
  },
  {
    "Id": 133,
    "Name": "OLD",
    "FatherCategoryId": 132,
    "Title": "",
    "Description": "",
    "Keywords": "",
    "IsActive": false,
    "LomadeeCampaignCode": "",
    "AdWordsRemarketingCode": "",
    "ShowInStoreFront": false,
    "ShowBrandFilter": false,
    "ActiveStoreFrontLink": true,
    "GlobalCategoryId": 536,
    "StockKeepingUnitSelectionMode": "LIST",
    "Score": null,
    "LinkId": "OLD",
    "HasChildren": true
  },
  {
    "Id": 160,
    "Name": "Bird Baths, Houses & Feeders",
    "FatherCategoryId": 115,
    "Title": "",
    "Description": "",
    "Keywords": "",
    "IsActive": false,
    "LomadeeCampaignCode": "",
    "AdWordsRemarketingCode": "",
    "ShowInStoreFront": false,
    "ShowBrandFilter": false,
    "ActiveStoreFrontLink": true,
    "GlobalCategoryId": 536,
    "StockKeepingUnitSelectionMode": "LIST",
    "Score": null,
    "LinkId": "Bird-Baths-Houses---Feeders",
    "HasChildren": false
  },
  {
    "Id": 159,
    "Name": "FAIRIES",
    "FatherCategoryId": 130,
    "Title": "",
    "Description": "",
    "Keywords": "",
    "IsActive": false,
    "LomadeeCampaignCode": "",
    "AdWordsRemarketingCode": "",
    "ShowInStoreFront": false,
    "ShowBrandFilter": false,
    "ActiveStoreFrontLink": true,
    "GlobalCategoryId": 536,
    "StockKeepingUnitSelectionMode": "LIST",
    "Score": null,
    "LinkId": "FAIRIES",
    "HasChildren": false
  },
  {
    "Id": 135,
    "Name": "Home Accents",
    "FatherCategoryId": 116,
    "Title": "",
    "Description": "",
    "Keywords": "",
    "IsActive": false,
    "LomadeeCampaignCode": "",
    "AdWordsRemarketingCode": "",
    "ShowInStoreFront": false,
    "ShowBrandFilter": false,
    "ActiveStoreFrontLink": true,
    "GlobalCategoryId": 536,
    "StockKeepingUnitSelectionMode": "LIST",
    "Score": null,
    "LinkId": "Home-Accents",
    "HasChildren": true
  },
  {
    "Id": 116,
    "Name": "HOME",
    "FatherCategoryId": 180,
    "Title": "",
    "Description": null,
    "Keywords": null,
    "IsActive": false,
    "LomadeeCampaignCode": null,
    "AdWordsRemarketingCode": null,
    "ShowInStoreFront": false,
    "ShowBrandFilter": false,
    "ActiveStoreFrontLink": false,
    "GlobalCategoryId": 0,
    "StockKeepingUnitSelectionMode": "LIST",
    "Score": null,
    "LinkId": "HOME",
    "HasChildren": true
  },
  {
    "Id": 122,
    "Name": "EGYPTIAN",
    "FatherCategoryId": 180,
    "Title": "",
    "Description": null,
    "Keywords": null,
    "IsActive": false,
    "LomadeeCampaignCode": null,
    "AdWordsRemarketingCode": null,
    "ShowInStoreFront": false,
    "ShowBrandFilter": false,
    "ActiveStoreFrontLink": false,
    "GlobalCategoryId": 0,
    "StockKeepingUnitSelectionMode": "LIST",
    "Score": null,
    "LinkId": "EGYPTIAN",
    "HasChildren": true
  },
  {
    "Id": 156,
    "Name": "Gargoyles",
    "FatherCategoryId": 121,
    "Title": "",
    "Description": "",
    "Keywords": "",
    "IsActive": false,
    "LomadeeCampaignCode": "",
    "AdWordsRemarketingCode": "",
    "ShowInStoreFront": false,
    "ShowBrandFilter": false,
    "ActiveStoreFrontLink": true,
    "GlobalCategoryId": 536,
    "StockKeepingUnitSelectionMode": "LIST",
    "Score": null,
    "LinkId": "Gargoyles",
    "HasChildren": false
  },
  {
    "Id": 121,
    "Name": "GOTHIC",
    "FatherCategoryId": 180,
    "Title": "",
    "Description": null,
    "Keywords": null,
    "IsActive": false,
    "LomadeeCampaignCode": null,
    "AdWordsRemarketingCode": null,
    "ShowInStoreFront": false,
    "ShowBrandFilter": false,
    "ActiveStoreFrontLink": false,
    "GlobalCategoryId": 0,
    "StockKeepingUnitSelectionMode": "LIST",
    "Score": null,
    "LinkId": "GOTHIC",
    "HasChildren": true
  },
  {
    "Id": 119,
    "Name": "Electronics",
    "FatherCategoryId": 103,
    "Title": "",
    "Description": "",
    "Keywords": "",
    "IsActive": false,
    "LomadeeCampaignCode": "",
    "AdWordsRemarketingCode": "",
    "ShowInStoreFront": false,
    "ShowBrandFilter": false,
    "ActiveStoreFrontLink": false,
    "GlobalCategoryId": 222,
    "StockKeepingUnitSelectionMode": "LIST",
    "Score": null,
    "LinkId": "Electronics",
    "HasChildren": false
  },
  {
    "Id": 130,
    "Name": "Fantasy Statues",
    "FatherCategoryId": 115,
    "Title": "",
    "Description": "",
    "Keywords": "",
    "IsActive": false,
    "LomadeeCampaignCode": "",
    "AdWordsRemarketingCode": "",
    "ShowInStoreFront": false,
    "ShowBrandFilter": false,
    "ActiveStoreFrontLink": true,
    "GlobalCategoryId": 536,
    "StockKeepingUnitSelectionMode": "LIST",
    "Score": null,
    "LinkId": "Fantasy-Statues",
    "HasChildren": true
  },
  {
    "Id": 134,
    "Name": "Indoor Statues",
    "FatherCategoryId": 116,
    "Title": "",
    "Description": "",
    "Keywords": "",
    "IsActive": false,
    "LomadeeCampaignCode": "",
    "AdWordsRemarketingCode": "",
    "ShowInStoreFront": false,
    "ShowBrandFilter": false,
    "ActiveStoreFrontLink": true,
    "GlobalCategoryId": 536,
    "StockKeepingUnitSelectionMode": "LIST",
    "Score": null,
    "LinkId": "Indoor-Statues",
    "HasChildren": false
  },
  {
    "Id": 149,
    "Name": "African Animals",
    "FatherCategoryId": 126,
    "Title": "",
    "Description": "",
    "Keywords": "",
    "IsActive": false,
    "LomadeeCampaignCode": "",
    "AdWordsRemarketingCode": "",
    "ShowInStoreFront": false,
    "ShowBrandFilter": false,
    "ActiveStoreFrontLink": true,
    "GlobalCategoryId": 536,
    "StockKeepingUnitSelectionMode": "LIST",
    "Score": null,
    "LinkId": "African-Animals",
    "HasChildren": false
  },
  {
    "Id": 120,
    "Name": "Electronics",
    "FatherCategoryId": 103,
    "Title": "",
    "Description": "",
    "Keywords": "Electronics",
    "IsActive": false,
    "LomadeeCampaignCode": "",
    "AdWordsRemarketingCode": "",
    "ShowInStoreFront": false,
    "ShowBrandFilter": false,
    "ActiveStoreFrontLink": false,
    "GlobalCategoryId": 222,
    "StockKeepingUnitSelectionMode": "LIST",
    "Score": null,
    "LinkId": "Electronics",
    "HasChildren": false
  },
  {
    "Id": 106,
    "Name": "Washers & Dryers",
    "FatherCategoryId": 101,
    "Title": "Washers & Dryers",
    "Description": "This is a generic description of a Category.",
    "Keywords": "Washers & Dryers",
    "IsActive": true,
    "LomadeeCampaignCode": "",
    "AdWordsRemarketingCode": "",
    "ShowInStoreFront": true,
    "ShowBrandFilter": true,
    "ActiveStoreFrontLink": true,
    "GlobalCategoryId": 5605,
    "StockKeepingUnitSelectionMode": "LIST",
    "Score": 3,
    "LinkId": "Washers---Dryers",
    "HasChildren": false
  },
  {
    "Id": 137,
    "Name": "Wall Decor",
    "FatherCategoryId": 116,
    "Title": "",
    "Description": "",
    "Keywords": "",
    "IsActive": false,
    "LomadeeCampaignCode": "",
    "AdWordsRemarketingCode": "",
    "ShowInStoreFront": false,
    "ShowBrandFilter": false,
    "ActiveStoreFrontLink": true,
    "GlobalCategoryId": 536,
    "StockKeepingUnitSelectionMode": "LIST",
    "Score": null,
    "LinkId": "Wall-Decor",
    "HasChildren": false
  },
  {
    "Id": 148,
    "Name": "Farm Animals",
    "FatherCategoryId": 126,
    "Title": "",
    "Description": "",
    "Keywords": "",
    "IsActive": false,
    "LomadeeCampaignCode": "",
    "AdWordsRemarketingCode": "",
    "ShowInStoreFront": false,
    "ShowBrandFilter": false,
    "ActiveStoreFrontLink": true,
    "GlobalCategoryId": 536,
    "StockKeepingUnitSelectionMode": "LIST",
    "Score": null,
    "LinkId": "Farm-Animals",
    "HasChildren": false
  },
  {
    "Id": 108,
    "Name": "Toasters & Grills",
    "FatherCategoryId": 102,
    "Title": "Toasters & Grills",
    "Description": "This is a generic description of a Category.",
    "Keywords": "Toasters & Grills",
    "IsActive": false,
    "LomadeeCampaignCode": "",
    "AdWordsRemarketingCode": "",
    "ShowInStoreFront": true,
    "ShowBrandFilter": true,
    "ActiveStoreFrontLink": true,
    "GlobalCategoryId": 0,
    "StockKeepingUnitSelectionMode": "SPECIFICATION",
    "Score": 3,
    "LinkId": "Toasters---Grills",
    "HasChildren": false
  },
  {
    "Id": 126,
    "Name": "Animal Statues",
    "FatherCategoryId": 115,
    "Title": "",
    "Description": "",
    "Keywords": "",
    "IsActive": false,
    "LomadeeCampaignCode": "",
    "AdWordsRemarketingCode": "",
    "ShowInStoreFront": false,
    "ShowBrandFilter": false,
    "ActiveStoreFrontLink": true,
    "GlobalCategoryId": 536,
    "StockKeepingUnitSelectionMode": "LIST",
    "Score": null,
    "LinkId": "Animal-Statues",
    "HasChildren": true
  },
  {
    "Id": 132,
    "Name": "NEW",
    "FatherCategoryId": 123,
    "Title": "",
    "Description": "",
    "Keywords": "",
    "IsActive": false,
    "LomadeeCampaignCode": "",
    "AdWordsRemarketingCode": "",
    "ShowInStoreFront": false,
    "ShowBrandFilter": false,
    "ActiveStoreFrontLink": false,
    "GlobalCategoryId": 536,
    "StockKeepingUnitSelectionMode": "LIST",
    "Score": null,
    "LinkId": "NEW",
    "HasChildren": true
  },
  {
    "Id": 150,
    "Name": "Classic Animals",
    "FatherCategoryId": 126,
    "Title": "",
    "Description": "",
    "Keywords": "",
    "IsActive": false,
    "LomadeeCampaignCode": "",
    "AdWordsRemarketingCode": "",
    "ShowInStoreFront": false,
    "ShowBrandFilter": false,
    "ActiveStoreFrontLink": true,
    "GlobalCategoryId": 536,
    "StockKeepingUnitSelectionMode": "LIST",
    "Score": null,
    "LinkId": "Classic-Animals",
    "HasChildren": false
  },
  {
    "Id": 125,
    "Name": "SALE",
    "FatherCategoryId": 180,
    "Title": "",
    "Description": null,
    "Keywords": null,
    "IsActive": false,
    "LomadeeCampaignCode": null,
    "AdWordsRemarketingCode": null,
    "ShowInStoreFront": false,
    "ShowBrandFilter": false,
    "ActiveStoreFrontLink": false,
    "GlobalCategoryId": 0,
    "StockKeepingUnitSelectionMode": "LIST",
    "Score": null,
    "LinkId": "SALE",
    "HasChildren": false
  },
  {
    "Id": 180,
    "Name": "category5",
    "FatherCategoryId": null,
    "Title": "Shop",
    "Description": "Shop wallpapers & Murals",
    "Keywords": "Shop",
    "IsActive": true,
    "LomadeeCampaignCode": "",
    "AdWordsRemarketingCode": "",
    "ShowInStoreFront": false,
    "ShowBrandFilter": false,
    "ActiveStoreFrontLink": false,
    "GlobalCategoryId": 1,
    "StockKeepingUnitSelectionMode": "SPECIFICATION",
    "Score": null,
    "LinkId": "category5",
    "HasChildren": true
  },
  {
    "Id": 169,
    "Name": "Prescription Drugs",
    "FatherCategoryId": 180,
    "Title": "Prescription Drugs",
    "Description": null,
    "Keywords": null,
    "IsActive": false,
    "LomadeeCampaignCode": null,
    "AdWordsRemarketingCode": null,
    "ShowInStoreFront": false,
    "ShowBrandFilter": false,
    "ActiveStoreFrontLink": false,
    "GlobalCategoryId": 0,
    "StockKeepingUnitSelectionMode": "LIST",
    "Score": null,
    "LinkId": "Prescription-Drugs",
    "HasChildren": false
  },
  {
    "Id": 176,
    "Name": "Kids",
    "FatherCategoryId": 180,
    "Title": "Kids",
    "Description": null,
    "Keywords": null,
    "IsActive": false,
    "LomadeeCampaignCode": null,
    "AdWordsRemarketingCode": null,
    "ShowInStoreFront": false,
    "ShowBrandFilter": false,
    "ActiveStoreFrontLink": false,
    "GlobalCategoryId": 0,
    "StockKeepingUnitSelectionMode": "COMBO",
    "Score": null,
    "LinkId": "Kids",
    "HasChildren": true
  },
  {
    "Id": 165,
    "Name": "Animals",
    "FatherCategoryId": 135,
    "Title": "",
    "Description": "",
    "Keywords": "",
    "IsActive": false,
    "LomadeeCampaignCode": "",
    "AdWordsRemarketingCode": "",
    "ShowInStoreFront": false,
    "ShowBrandFilter": false,
    "ActiveStoreFrontLink": true,
    "GlobalCategoryId": 536,
    "StockKeepingUnitSelectionMode": "LIST",
    "Score": null,
    "LinkId": "Animals",
    "HasChildren": false
  },
  {
    "Id": 155,
    "Name": "Dragons",
    "FatherCategoryId": 121,
    "Title": "",
    "Description": "",
    "Keywords": "",
    "IsActive": false,
    "LomadeeCampaignCode": "",
    "AdWordsRemarketingCode": "",
    "ShowInStoreFront": false,
    "ShowBrandFilter": false,
    "ActiveStoreFrontLink": true,
    "GlobalCategoryId": 536,
    "StockKeepingUnitSelectionMode": "LIST",
    "Score": null,
    "LinkId": "Dragons",
    "HasChildren": false
  },
  {
    "Id": 185,
    "Name": "c",
    "FatherCategoryId": null,
    "Title": "Shop",
    "Description": "Shop wallpapers & Murals",
    "Keywords": "Shop",
    "IsActive": true,
    "LomadeeCampaignCode": "",
    "AdWordsRemarketingCode": "",
    "ShowInStoreFront": false,
    "ShowBrandFilter": false,
    "ActiveStoreFrontLink": false,
    "GlobalCategoryId": 1,
    "StockKeepingUnitSelectionMode": "SPECIFICATION",
    "Score": null,
    "LinkId": "c",
    "HasChildren": false
  },
  {
    "Id": 168,
    "Name": "Car",
    "FatherCategoryId": 180,
    "Title": "cars",
    "Description": null,
    "Keywords": null,
    "IsActive": false,
    "LomadeeCampaignCode": null,
    "AdWordsRemarketingCode": null,
    "ShowInStoreFront": false,
    "ShowBrandFilter": false,
    "ActiveStoreFrontLink": false,
    "GlobalCategoryId": 0,
    "StockKeepingUnitSelectionMode": "LIST",
    "Score": null,
    "LinkId": "Car",
    "HasChildren": false
  },
  {
    "Id": 124,
    "Name": "NEW",
    "FatherCategoryId": 180,
    "Title": "",
    "Description": null,
    "Keywords": null,
    "IsActive": false,
    "LomadeeCampaignCode": null,
    "AdWordsRemarketingCode": null,
    "ShowInStoreFront": false,
    "ShowBrandFilter": false,
    "ActiveStoreFrontLink": false,
    "GlobalCategoryId": 0,
    "StockKeepingUnitSelectionMode": "LIST",
    "Score": null,
    "LinkId": "NEW",
    "HasChildren": false
  },
  {
    "Id": 144,
    "Name": "CHECK",
    "FatherCategoryId": 133,
    "Title": "",
    "Description": "",
    "Keywords": "",
    "IsActive": false,
    "LomadeeCampaignCode": "",
    "AdWordsRemarketingCode": "",
    "ShowInStoreFront": false,
    "ShowBrandFilter": false,
    "ActiveStoreFrontLink": true,
    "GlobalCategoryId": 536,
    "StockKeepingUnitSelectionMode": "LIST",
    "Score": null,
    "LinkId": "CHECK",
    "HasChildren": false
  },
  {
    "Id": 177,
    "Name": "Shoes",
    "FatherCategoryId": 176,
    "Title": "Shoes",
    "Description": "Kids Shoes",
    "Keywords": "Sneakers, boots,loafer,flip-flops,shoe,slipper",
    "IsActive": false,
    "LomadeeCampaignCode": "",
    "AdWordsRemarketingCode": "",
    "ShowInStoreFront": true,
    "ShowBrandFilter": true,
    "ActiveStoreFrontLink": true,
    "GlobalCategoryId": 166,
    "StockKeepingUnitSelectionMode": "COMBO",
    "Score": null,
    "LinkId": "Shoes",
    "HasChildren": true
  },
  {
    "Id": 181,
    "Name": "category1",
    "FatherCategoryId": null,
    "Title": "Shop",
    "Description": "Shop wallpapers & Murals",
    "Keywords": "Shop",
    "IsActive": true,
    "LomadeeCampaignCode": "",
    "AdWordsRemarketingCode": "",
    "ShowInStoreFront": false,
    "ShowBrandFilter": false,
    "ActiveStoreFrontLink": true,
    "GlobalCategoryId": 1,
    "StockKeepingUnitSelectionMode": "SPECIFICATION",
    "Score": null,
    "LinkId": "category1",
    "HasChildren": false
  },
  {
    "Id": 182,
    "Name": "c",
    "FatherCategoryId": null,
    "Title": "Shop",
    "Description": "Shop wallpapers & Murals",
    "Keywords": "Shop",
    "IsActive": false,
    "LomadeeCampaignCode": "",
    "AdWordsRemarketingCode": "",
    "ShowInStoreFront": false,
    "ShowBrandFilter": false,
    "ActiveStoreFrontLink": false,
    "GlobalCategoryId": 1,
    "StockKeepingUnitSelectionMode": "LIST",
    "Score": null,
    "LinkId": "c",
    "HasChildren": false
  },
  {
    "Id": 183,
    "Name": "c",
    "FatherCategoryId": null,
    "Title": "Shop",
    "Description": "Shop wallpapers & Murals",
    "Keywords": "Shop",
    "IsActive": false,
    "LomadeeCampaignCode": null,
    "AdWordsRemarketingCode": null,
    "ShowInStoreFront": false,
    "ShowBrandFilter": false,
    "ActiveStoreFrontLink": false,
    "GlobalCategoryId": 1,
    "StockKeepingUnitSelectionMode": "SPECIFICATION",
    "Score": null,
    "LinkId": "c",
    "HasChildren": false
  },
  {
    "Id": 171,
    "Name": "Personal Care",
    "FatherCategoryId": 170,
    "Title": "Personal Care",
    "Description": "Personal Care",
    "Keywords": "Personal Care",
    "IsActive": false,
    "LomadeeCampaignCode": "",
    "AdWordsRemarketingCode": "",
    "ShowInStoreFront": true,
    "ShowBrandFilter": true,
    "ActiveStoreFrontLink": true,
    "GlobalCategoryId": 491,
    "StockKeepingUnitSelectionMode": "LIST",
    "Score": null,
    "LinkId": "Personal-Care",
    "HasChildren": true
  },
  {
    "Id": 187,
    "Name": "category4",
    "FatherCategoryId": null,
    "Title": "Shop",
    "Description": "Shop wallpapers & Murals",
    "Keywords": "Shop",
    "IsActive": true,
    "LomadeeCampaignCode": "",
    "AdWordsRemarketingCode": "",
    "ShowInStoreFront": false,
    "ShowBrandFilter": false,
    "ActiveStoreFrontLink": false,
    "GlobalCategoryId": 1,
    "StockKeepingUnitSelectionMode": "SPECIFICATION",
    "Score": null,
    "LinkId": "category4",
    "HasChildren": false
  },
  {
    "Id": 166,
    "Name": "Religious",
    "FatherCategoryId": 135,
    "Title": "",
    "Description": "",
    "Keywords": "",
    "IsActive": false,
    "LomadeeCampaignCode": "",
    "AdWordsRemarketingCode": "",
    "ShowInStoreFront": false,
    "ShowBrandFilter": false,
    "ActiveStoreFrontLink": true,
    "GlobalCategoryId": 536,
    "StockKeepingUnitSelectionMode": "LIST",
    "Score": null,
    "LinkId": "Religious",
    "HasChildren": false
  },
  {
    "Id": 161,
    "Name": "Children Statues",
    "FatherCategoryId": 115,
    "Title": "",
    "Description": "",
    "Keywords": "",
    "IsActive": false,
    "LomadeeCampaignCode": "",
    "AdWordsRemarketingCode": "",
    "ShowInStoreFront": false,
    "ShowBrandFilter": false,
    "ActiveStoreFrontLink": true,
    "GlobalCategoryId": 536,
    "StockKeepingUnitSelectionMode": "LIST",
    "Score": null,
    "LinkId": "Children-Statues",
    "HasChildren": false
  },
  {
    "Id": 175,
    "Name": "Boots",
    "FatherCategoryId": 174,
    "Title": "Boots",
    "Description": "Boots",
    "Keywords": "Wellington, gumboot, knee boot, thigh boot, half-boot",
    "IsActive": false,
    "LomadeeCampaignCode": "",
    "AdWordsRemarketingCode": "",
    "ShowInStoreFront": true,
    "ShowBrandFilter": true,
    "ActiveStoreFrontLink": true,
    "GlobalCategoryId": 166,
    "StockKeepingUnitSelectionMode": "LIST",
    "Score": null,
    "LinkId": "Boots",
    "HasChildren": false
  },
  {
    "Id": 179,
    "Name": "Singles",
    "FatherCategoryId": null,
    "Title": "",
    "Description": "",
    "Keywords": "Single,Singles",
    "IsActive": false,
    "LomadeeCampaignCode": "",
    "AdWordsRemarketingCode": "",
    "ShowInStoreFront": false,
    "ShowBrandFilter": false,
    "ActiveStoreFrontLink": false,
    "GlobalCategoryId": 1,
    "StockKeepingUnitSelectionMode": "LIST",
    "Score": null,
    "LinkId": "Singles",
    "HasChildren": false
  },
  {
    "Id": 153,
    "Name": "CLASSIC",
    "FatherCategoryId": 127,
    "Title": "",
    "Description": "",
    "Keywords": "",
    "IsActive": false,
    "LomadeeCampaignCode": "",
    "AdWordsRemarketingCode": "",
    "ShowInStoreFront": false,
    "ShowBrandFilter": false,
    "ActiveStoreFrontLink": true,
    "GlobalCategoryId": 536,
    "StockKeepingUnitSelectionMode": "LIST",
    "Score": null,
    "LinkId": "CLASSIC",
    "HasChildren": false
  },
  {
    "Id": 118,
    "Name": "THEMES",
    "FatherCategoryId": 180,
    "Title": "",
    "Description": null,
    "Keywords": null,
    "IsActive": false,
    "LomadeeCampaignCode": null,
    "AdWordsRemarketingCode": null,
    "ShowInStoreFront": false,
    "ShowBrandFilter": false,
    "ActiveStoreFrontLink": false,
    "GlobalCategoryId": 0,
    "StockKeepingUnitSelectionMode": "LIST",
    "Score": null,
    "LinkId": "THEMES",
    "HasChildren": false
  },
  {
    "Id": 170,
    "Name": "Hygiene",
    "FatherCategoryId": 180,
    "Title": "Hygiene",
    "Description": null,
    "Keywords": null,
    "IsActive": false,
    "LomadeeCampaignCode": null,
    "AdWordsRemarketingCode": null,
    "ShowInStoreFront": false,
    "ShowBrandFilter": false,
    "ActiveStoreFrontLink": false,
    "GlobalCategoryId": 0,
    "StockKeepingUnitSelectionMode": "LIST",
    "Score": null,
    "LinkId": "Hygiene",
    "HasChildren": true
  },
  {
    "Id": 167,
    "Name": "electronics",
    "FatherCategoryId": 180,
    "Title": "electronics",
    "Description": null,
    "Keywords": null,
    "IsActive": false,
    "LomadeeCampaignCode": null,
    "AdWordsRemarketingCode": null,
    "ShowInStoreFront": false,
    "ShowBrandFilter": false,
    "ActiveStoreFrontLink": false,
    "GlobalCategoryId": 0,
    "StockKeepingUnitSelectionMode": "LIST",
    "Score": null,
    "LinkId": "electronics",
    "HasChildren": false
  },
  {
    "Id": 138,
    "Name": "Lamps & Light Fixtures",
    "FatherCategoryId": 116,
    "Title": "",
    "Description": "",
    "Keywords": "",
    "IsActive": false,
    "LomadeeCampaignCode": "",
    "AdWordsRemarketingCode": "",
    "ShowInStoreFront": false,
    "ShowBrandFilter": false,
    "ActiveStoreFrontLink": true,
    "GlobalCategoryId": 536,
    "StockKeepingUnitSelectionMode": "LIST",
    "Score": null,
    "LinkId": "Lamps---Light-Fixtures",
    "HasChildren": false
  },
  {
    "Id": 136,
    "Name": "Decorative Walking Sticks",
    "FatherCategoryId": 116,
    "Title": "",
    "Description": "",
    "Keywords": "",
    "IsActive": false,
    "LomadeeCampaignCode": "",
    "AdWordsRemarketingCode": "",
    "ShowInStoreFront": false,
    "ShowBrandFilter": false,
    "ActiveStoreFrontLink": true,
    "GlobalCategoryId": 536,
    "StockKeepingUnitSelectionMode": "LIST",
    "Score": null,
    "LinkId": "Decorative-Walking-Sticks",
    "HasChildren": false
  },
  {
    "Id": 154,
    "Name": "ASIAN",
    "FatherCategoryId": 127,
    "Title": "",
    "Description": "",
    "Keywords": "",
    "IsActive": false,
    "LomadeeCampaignCode": "",
    "AdWordsRemarketingCode": "",
    "ShowInStoreFront": false,
    "ShowBrandFilter": false,
    "ActiveStoreFrontLink": true,
    "GlobalCategoryId": 536,
    "StockKeepingUnitSelectionMode": "LIST",
    "Score": null,
    "LinkId": "ASIAN",
    "HasChildren": false
  },
  {
    "Id": 173,
    "Name": "Mens",
    "FatherCategoryId": 180,
    "Title": "Mens",
    "Description": null,
    "Keywords": null,
    "IsActive": false,
    "LomadeeCampaignCode": null,
    "AdWordsRemarketingCode": null,
    "ShowInStoreFront": false,
    "ShowBrandFilter": false,
    "ActiveStoreFrontLink": false,
    "GlobalCategoryId": 0,
    "StockKeepingUnitSelectionMode": "LIST",
    "Score": null,
    "LinkId": "Mens",
    "HasChildren": true
  }
]
